jaldt/__init__.py
jaldt-1.0.0.dist-info/LICENSE
jaldt-1.0.0.dist-info/METADATA
jaldt-1.0.0.dist-info/WHEEL
jaldt-1.0.0.dist-info/top_level.txt
jaldt-1.0.0.dist-info/RECORD
