Metadata-Version: 2.1
Name: jaldt
Version: 1.0.0
Summary: Jaldt is a package for working with date and time based on Jalali calendar and date.
Home-page: https://github.com/mimseyedi/Jaldt
Author: mimseyedi
Author-email: mim.seyedi@gmail.com
Classifier: Programming Language :: Python :: 3
Classifier: License :: OSI Approved :: MIT License
Classifier: Operating System :: OS Independent
Requires-Python: >=3.6
License-File: LICENSE
